causing/__init__.py
causing/graph.py
causing/model.py
causing/utils.py
causing-2.4.6.dist-info/licenses/LICENSE.md
tests/__init__.py
tests/test_estimate.py
tests/test_model.py
tests/utils.py
tests/examples/__init__.py
tests/examples/models.py
causing-2.4.6.dist-info/METADATA
causing-2.4.6.dist-info/WHEEL
causing-2.4.6.dist-info/top_level.txt
causing-2.4.6.dist-info/RECORD
