Metadata-Version: 2.4
Name: causing
Version: 2.4.6
Summary: Causing: CAUSal INterpretation using Graphs
Home-page: https://github.com/realrate/Causing
Author: Dr. Holger Bartel
Author-email: holger.bartel@realrate.ai
Classifier: Programming Language :: Python :: 3
Classifier: License :: OSI Approved :: MIT License
Classifier: Operating System :: OS Independent
Requires-Python: >=3.9
License-File: LICENSE.md
Requires-Dist: numpy~=1.23
Requires-Dist: pandas~=1.3
Requires-Dist: scipy~=1.9
Requires-Dist: sympy~=1.5
Requires-Dist: networkx~=2.7
Requires-Dist: pre-commit
Dynamic: author
Dynamic: author-email
Dynamic: classifier
Dynamic: description
Dynamic: description-content-type
Dynamic: home-page
Dynamic: license-file
Dynamic: requires-dist
Dynamic: requires-python
Dynamic: summary
